dogpt.py
dogpt-1.0.0.dist-info/LICENSE
dogpt-1.0.0.dist-info/METADATA
dogpt-1.0.0.dist-info/WHEEL
dogpt-1.0.0.dist-info/entry_points.txt
dogpt-1.0.0.dist-info/top_level.txt
dogpt-1.0.0.dist-info/RECORD
