Metadata-Version: 2.1
Name: dogpt
Version: 1.0.0
Summary: Advanced AI, but for dogs. 🐶
Home-page: https://github.com/ntoll/dogpt
Author: Nicholas H.Tollervey
Author-email: ntoll@ntoll.org
License: MIT
Platform: UNKNOWN
Classifier: Development Status :: 5 - Production/Stable
Classifier: Environment :: Console
Classifier: Intended Audience :: Developers
Classifier: Intended Audience :: Education
Classifier: License :: OSI Approved :: MIT License
Classifier: Natural Language :: English
Classifier: Programming Language :: Python :: 3.5
Classifier: Topic :: Communications
Classifier: Topic :: Software Development :: Internationalization
